riotapiutilities/__init__.py
riotapiutilities/api.py
riotapiutilities/consts.py
riotapiutilities-1.2.1.dist-info/LICENSE
riotapiutilities-1.2.1.dist-info/METADATA
riotapiutilities-1.2.1.dist-info/WHEEL
riotapiutilities-1.2.1.dist-info/top_level.txt
riotapiutilities-1.2.1.dist-info/RECORD
